bloodmoon/__init__.py
bloodmoon/coords.py
bloodmoon/images.py
bloodmoon/io.py
bloodmoon/mask.py
bloodmoon/optim.py
bloodmoon/types.py
bloodmoon/utils.py
bloodmoon/assets/__init__.py
bloodmoon/assets/wfm_mask.fits
bloodmoon-0.1.0.dist-info/METADATA
bloodmoon-0.1.0.dist-info/WHEEL
bloodmoon-0.1.0.dist-info/licenses/LICENSE.txt
bloodmoon-0.1.0.dist-info/RECORD
